[
    {"temp": 30, "humidity": 85, "rainfall": 300, "soil_moisture": 35, "n": 60, "p": 30, "k": 40, "disease": "bacterial blight"},
    {"temp": 29, "humidity": 88, "rainfall": 320, "soil_moisture": 38, "n": 58, "p": 32, "k": 42, "disease": "bacterial blight"},
    {"temp": 31, "humidity": 83, "rainfall": 290, "soil_moisture": 33, "n": 55, "p": 33, "k": 45, "disease": "bacterial blight"},
    {"temp": 28, "humidity": 90, "rainfall": 310, "soil_moisture": 36, "n": 61, "p": 31, "k": 41, "disease": "bacterial blight"},
    {"temp": 30, "humidity": 87, "rainfall": 300, "soil_moisture": 34, "n": 59, "p": 34, "k": 43, "disease": "bacterial blight"},
    {"temp": 32, "humidity": 85, "rainfall": 295, "soil_moisture": 37, "n": 57, "p": 29, "k": 40, "disease": "bacterial blight"},
    {"temp": 30, "humidity": 89, "rainfall": 305, "soil_moisture": 32, "n": 60, "p": 30, "k": 39, "disease": "bacterial blight"},
    {"temp": 29, "humidity": 84, "rainfall": 315, "soil_moisture": 39, "n": 58, "p": 35, "k": 42, "disease": "bacterial blight"},
    {"temp": 31, "humidity": 88, "rainfall": 320, "soil_moisture": 34, "n": 60, "p": 33, "k": 41, "disease": "bacterial blight"},
    {"temp": 30, "humidity": 86, "rainfall": 300, "soil_moisture": 36, "n": 59, "p": 30, "k": 40, "disease": "bacterial blight"},
    
    {"temp": 27, "humidity": 80, "rainfall": 280, "soil_moisture": 28, "n": 55, "p": 35, "k": 45, "disease": "bacterial leaf streak"},
    {"temp": 28, "humidity": 82, "rainfall": 270, "soil_moisture": 30, "n": 57, "p": 32, "k": 44, "disease": "bacterial leaf streak"},
    {"temp": 29, "humidity": 81, "rainfall": 285, "soil_moisture": 27, "n": 54, "p": 36, "k": 43, "disease": "bacterial leaf streak"},
    {"temp": 27, "humidity": 83, "rainfall": 275, "soil_moisture": 29, "n": 55, "p": 34, "k": 46, "disease": "bacterial leaf streak"},
    {"temp": 28, "humidity": 80, "rainfall": 290, "soil_moisture": 31, "n": 58, "p": 30, "k": 42, "disease": "bacterial leaf streak"},
    {"temp": 29, "humidity": 85, "rainfall": 295, "soil_moisture": 32, "n": 57, "p": 31, "k": 43, "disease": "bacterial leaf streak"},
    {"temp": 28, "humidity": 82, "rainfall": 280, "soil_moisture": 28, "n": 56, "p": 33, "k": 44, "disease": "bacterial leaf streak"},
    {"temp": 27, "humidity": 81, "rainfall": 285, "soil_moisture": 30, "n": 55, "p": 35, "k": 45, "disease": "bacterial leaf streak"},
    {"temp": 28, "humidity": 83, "rainfall": 275, "soil_moisture": 29, "n": 57, "p": 32, "k": 43, "disease": "bacterial leaf streak"},
    {"temp": 29, "humidity": 84, "rainfall": 290, "soil_moisture": 31, "n": 56, "p": 34, "k": 46, "disease": "bacterial leaf streak"},
    
    {"temp": 26, "humidity": 90, "rainfall": 340, "soil_moisture": 40, "n": 65, "p": 28, "k": 38, "disease": "foot rot"},
    {"temp": 25, "humidity": 88, "rainfall": 330, "soil_moisture": 42, "n": 66, "p": 30, "k": 37, "disease": "foot rot"},
    {"temp": 24, "humidity": 91, "rainfall": 350, "soil_moisture": 44, "n": 67, "p": 29, "k": 36, "disease": "foot rot"},
    {"temp": 26, "humidity": 89, "rainfall": 360, "soil_moisture": 41, "n": 66, "p": 31, "k": 39, "disease": "foot rot"},
    {"temp": 25, "humidity": 92, "rainfall": 345, "soil_moisture": 39, "n": 68, "p": 32, "k": 38, "disease": "foot rot"},
    {"temp": 24, "humidity": 87, "rainfall": 355, "soil_moisture": 43, "n": 65, "p": 30, "k": 37, "disease": "foot rot"},
    {"temp": 26, "humidity": 90, "rainfall": 340, "soil_moisture": 42, "n": 67, "p": 28, "k": 39, "disease": "foot rot"},
    {"temp": 25, "humidity": 89, "rainfall": 330, "soil_moisture": 41, "n": 66, "p": 31, "k": 38, "disease": "foot rot"},
    {"temp": 24, "humidity": 91, "rainfall": 350, "soil_moisture": 44, "n": 68, "p": 29, "k": 36, "disease": "foot rot"},
    {"temp": 26, "humidity": 88, "rainfall": 345, "soil_moisture": 39, "n": 67, "p": 32, "k": 37, "disease": "foot rot"},
    
    {"temp": 28, "humidity": 70, "rainfall": 250, "soil_moisture": 30, "n": 50, "p": 40, "k": 45, "disease": "pecky rice"},
    {"temp": 27, "humidity": 72, "rainfall": 260, "soil_moisture": 32, "n": 52, "p": 42, "k": 46, "disease": "pecky rice"},
    {"temp": 29, "humidity": 68, "rainfall": 255, "soil_moisture": 33, "n": 51, "p": 43, "k": 44, "disease": "pecky rice"},
    {"temp": 28, "humidity": 69, "rainfall": 265, "soil_moisture": 34, "n": 53, "p": 41, "k": 47, "disease": "pecky rice"},
    {"temp": 29, "humidity": 71, "rainfall": 270, "soil_moisture": 35, "n": 54, "p": 40, "k": 46, "disease": "pecky rice"},
    {"temp": 29, "humidity": 71, "rainfall": 270, "soil_moisture": 35, "n": 54, "p": 40, "k": 46, "disease": "pecky rice"},
    {"temp": 28, "humidity": 70, "rainfall": 260, "soil_moisture": 33, "n": 50, "p": 41, "k": 45, "disease": "pecky rice"},
    {"temp": 27, "humidity": 72, "rainfall": 250, "soil_moisture": 34, "n": 52, "p": 42, "k": 47, "disease": "pecky rice"},
    {"temp": 29, "humidity": 68, "rainfall": 255, "soil_moisture": 32, "n": 51, "p": 43, "k": 44, "disease": "pecky rice"},
    {"temp": 28, "humidity": 69, "rainfall": 265, "soil_moisture": 35, "n": 53, "p": 41, "k": 46, "disease": "pecky rice"},

    {"temp": 25, "humidity": 78, "rainfall": 295, "soil_moisture": 37, "n": 62, "p": 28, "k": 39, "disease": "sheath brown rot"},
    {"temp": 26, "humidity": 80, "rainfall": 300, "soil_moisture": 36, "n": 63, "p": 30, "k": 40, "disease": "sheath brown rot"},
    {"temp": 24, "humidity": 79, "rainfall": 290, "soil_moisture": 38, "n": 64, "p": 29, "k": 41, "disease": "sheath brown rot"},
    {"temp": 25, "humidity": 77, "rainfall": 285, "soil_moisture": 37, "n": 65, "p": 31, "k": 39, "disease": "sheath brown rot"},
    {"temp": 26, "humidity": 81, "rainfall": 305, "soil_moisture": 39, "n": 66, "p": 32, "k": 38, "disease": "sheath brown rot"},
    {"temp": 24, "humidity": 79, "rainfall": 295, "soil_moisture": 40, "n": 62, "p": 30, "k": 41, "disease": "sheath brown rot"},
    {"temp": 25, "humidity": 78, "rainfall": 300, "soil_moisture": 37, "n": 63, "p": 31, "k": 40, "disease": "sheath brown rot"},
    {"temp": 26, "humidity": 80, "rainfall": 285, "soil_moisture": 36, "n": 62, "p": 29, "k": 39, "disease": "sheath brown rot"},
    {"temp": 24, "humidity": 82, "rainfall": 305, "soil_moisture": 38, "n": 64, "p": 28, "k": 40, "disease": "sheath brown rot"},
    {"temp": 25, "humidity": 79, "rainfall": 295, "soil_moisture": 37, "n": 63, "p": 32, "k": 41, "disease": "sheath brown rot"}
]
